genie2_pytorch/__init__.py
genie2_pytorch/genie2.py
genie2_pytorch-0.0.21.dist-info/METADATA
genie2_pytorch-0.0.21.dist-info/WHEEL
genie2_pytorch-0.0.21.dist-info/licenses/LICENSE
genie2_pytorch-0.0.21.dist-info/RECORD
