Metadata-Version: 2.4
Name: genie2-pytorch
Version: 0.0.21
Summary: Genie2
Project-URL: Homepage, https://pypi.org/project/genie2-pytorch/
Project-URL: Repository, https://github.com/lucidrains/genie2-pytorch
Author-email: Phil Wang <lucidrains@gmail.com>
License: MIT License
License-File: LICENSE
Keywords: artificial intelligence,attention mechanism,deep learning,transformers,world models
Classifier: Development Status :: 4 - Beta
Classifier: Intended Audience :: Developers
Classifier: License :: OSI Approved :: MIT License
Classifier: Programming Language :: Python :: 3.9
Classifier: Topic :: Scientific/Engineering :: Artificial Intelligence
Requires-Python: >=3.9
Requires-Dist: beartype
Requires-Dist: einops>=0.8.0
Requires-Dist: einx>=0.3.0
Requires-Dist: imagen-pytorch>=2.1.0
Requires-Dist: jaxtyping
Requires-Dist: ring-attention-pytorch
Requires-Dist: torch>=2.2
Requires-Dist: torchvision
Requires-Dist: vector-quantize-pytorch>=1.21.1
Requires-Dist: x-transformers>=1.43.4
Provides-Extra: examples
Provides-Extra: test
Requires-Dist: pytest; extra == 'test'
